LICENSE
MANIFEST.in
README.txt
setup.cfg
setup.py
TracGoogleSearch.egg-info/PKG-INFO
TracGoogleSearch.egg-info/SOURCES.txt
TracGoogleSearch.egg-info/dependency_links.txt
TracGoogleSearch.egg-info/entry_points.txt
TracGoogleSearch.egg-info/namespace_packages.txt
TracGoogleSearch.egg-info/requires.txt
TracGoogleSearch.egg-info/top_level.txt
tracext/__init__.py
tracext.google.search.egg-info/SOURCES.txt
tracext.google.search.egg-info/dependency_links.txt
tracext.google.search.egg-info/entry_points.txt
tracext.google.search.egg-info/namespace_packages.txt
tracext.google.search.egg-info/requires.txt
tracext.google.search.egg-info/top_level.txt
tracext/google/__init__.py
tracext/google/search/__init__.py
tracext/google/search/admin.py
tracext/google/search/search.py
tracext/google/search/htdocs/googlesearch.css
tracext/google/search/templates/google_search_admin.html
tracext/google/search/templates/google_search_form.html
tracext/google/search/templates/google_search_results.html