Metadata-Version: 1.0
Name: TracGoogleSearch
Version: 0.1.2
Summary: Google Adsense Search Plugin for Trac
Home-page: http://google.ufsoft.org
Author: Pedro Algarvio
Author-email: ufs@ufsoft.org
License: BSD
Download-URL: http://python.org/pypi/tracext.google.search
Keywords: adsense trac
Platform: OS Independent - Anywhere Python
Platform: Trac >=0.11 is known to run.
Classifier: Framework :: Trac
